Er1s/__init__.py
er1s-0.1.dist-info/METADATA
er1s-0.1.dist-info/WHEEL
er1s-0.1.dist-info/top_level.txt
er1s-0.1.dist-info/RECORD
