Metadata-Version: 2.1
Name: er1s
Version: 0.1
Summary: er1s
Home-page: http://github.com/eris9/eris9
Author: Eris9/Sakurai07
Author-email: blzzardst0rm@gmail.com
License: MIT
Platform: UNKNOWN
